mosaicai/__init__.py
mosaicai/client.py
mosaicai/exceptions.py
mosaicai/models/__init__.py
mosaicai/models/base.py
mosaicai/models/chatgpt.py
mosaicai/models/claude.py
mosaicai/models/gemini.py
mosaicai/models/perplexity.py
mosaicai/utils/api_key_manager.py
mosaicai/utils/logger.py
mosaicai-0.1.4.dist-info/LICENSE
mosaicai-0.1.4.dist-info/METADATA
mosaicai-0.1.4.dist-info/WHEEL
mosaicai-0.1.4.dist-info/top_level.txt
mosaicai-0.1.4.dist-info/RECORD
