Metadata-Version: 2.1
Name: mosaicai
Version: 0.1.4
Summary: A unified interface for multiple AI language models
Author-email: syukan3 <syun3ac@gmail.com>
License: MIT License
Project-URL: Homepage, https://github.com/syukan3/MosaicAI
Keywords: ai,language model,chatgpt,claude,gemini,perplexity
Classifier: Development Status :: 3 - Alpha
Classifier: Intended Audience :: Developers
Classifier: License :: OSI Approved :: MIT License
Classifier: Operating System :: OS Independent
Classifier: Programming Language :: Python :: 3
Classifier: Programming Language :: Python :: 3.7
Classifier: Programming Language :: Python :: 3.8
Classifier: Programming Language :: Python :: 3.9
Classifier: Programming Language :: Python :: 3.10
Requires-Python: >=3.7
License-File: LICENSE
Requires-Dist: anthropic==0.33.0
Requires-Dist: google-generativeai==0.7.2
Requires-Dist: openai==1.40.3
Requires-Dist: Pillow==10.4.0
Requires-Dist: python-dotenv==1.0.1
Requires-Dist: cryptography==43.0.0
Requires-Dist: pydantic==2.8.2
Provides-Extra: dev
Requires-Dist: pytest==8.3.2; extra == "dev"
